nagato.py
nagato-0.6.1.dist-info/METADATA
nagato-0.6.1.dist-info/WHEEL
nagato-0.6.1.dist-info/entry_points.txt
nagato-0.6.1.dist-info/top_level.txt
nagato-0.6.1.dist-info/RECORD
