Metadata-Version: 2.1
Name: nagato
Version: 0.6.1
Summary: Bypass korean firewall(warning.or.kr)
Home-page: https://github.com/kjwon15/nagato
Author: Kjwon15
Author-email: kjwonmail@gmail.com
License: GPLv3 or later
Platform: UNKNOWN
